{
    "images": [
        {
            "filename": "440.png",
            "caption": ""
        },
        {
            "filename": "441.png",
            "caption": ""
        },
        {
            "filename": "442.png",
            "caption": ""
        },
        {
            "filename": "443.png",
            "caption": ""
        },
        {
            "filename": "444.png",
            "caption": ""
        },
        {
            "filename": "445.png",
            "caption": ""
        },
        {
            "filename": "452.png",
            "caption": ""
        },
        {
            "filename": "453.png",
            "caption": ""
        },
        {
            "filename": "454.png",
            "caption": ""
        },
        {
            "filename": "455.png",
            "caption": ""
        },
        {
            "filename": "456.png",
            "caption": ""
        },
        {
            "filename": "457.png",
            "caption": ""
        },
        {
            "filename": "464.png",
            "caption": ""
        },
        {
            "filename": "465.png",
            "caption": ""
        },
        {
            "filename": "466.png",
            "caption": ""
        },
        {
            "filename": "467.png",
            "caption": ""
        },
        {
            "filename": "468.png",
            "caption": ""
        },
        {
            "filename": "469.png",
            "caption": ""
        },
        {
            "filename": "476.png",
            "caption": ""
        },
        {
            "filename": "477.png",
            "caption": ""
        },
        {
            "filename": "478.png",
            "caption": ""
        },
        {
            "filename": "479.png",
            "caption": ""
        },
        {
            "filename": "480.png",
            "caption": ""
        },
        {
            "filename": "481.png",
            "caption": ""
        },
        {
            "filename": "488.png",
            "caption": ""
        },
        {
            "filename": "489.png",
            "caption": ""
        },
        {
            "filename": "490.png",
            "caption": ""
        },
        {
            "filename": "491.png",
            "caption": ""
        },
        {
            "filename": "498.png",
            "caption": ""
        },
        {
            "filename": "499.png",
            "caption": ""
        },
        {
            "filename": "500.png",
            "caption": ""
        },
        {
            "filename": "501.png",
            "caption": ""
        },
        {
            "filename": "508.png",
            "caption": ""
        },
        {
            "filename": "509.png",
            "caption": ""
        },
        {
            "filename": "510.png",
            "caption": ""
        },
        {
            "filename": "511.png",
            "caption": ""
        },
        {
            "filename": "512.png",
            "caption": ""
        },
        {
            "filename": "513.png",
            "caption": ""
        },
        {
            "filename": "520.png",
            "caption": ""
        },
        {
            "filename": "527.png",
            "caption": ""
        },
        {
            "filename": "534.png",
            "caption": ""
        },
        {
            "filename": "541.png",
            "caption": ""
        },
        {
            "filename": "548.png",
            "caption": ""
        },
        {
            "filename": "555.png",
            "caption": ""
        },
        {
            "filename": "562.png",
            "caption": ""
        },
        {
            "filename": "569.png",
            "caption": ""
        },
        {
            "filename": "576.png",
            "caption": ""
        }
    ]
}